hmdriver2/__init__.py
hmdriver2/_client.py
hmdriver2/_gesture.py
hmdriver2/_screenrecord.py
hmdriver2/_swipe.py
hmdriver2/_uiobject.py
hmdriver2/_xpath.py
hmdriver2/assets/uitest_agent_v1.0.7.so
hmdriver2/assets/uitest_agent_v1.1.0.so
hmdriver2/driver.py
hmdriver2/exception.py
hmdriver2/hdc.py
hmdriver2/proto.py
hmdriver2/utils.py
hmdriver2-1.4.4.dist-info/LICENSE
hmdriver2-1.4.4.dist-info/METADATA
hmdriver2-1.4.4.dist-info/WHEEL
hmdriver2-1.4.4.dist-info/RECORD
