Metadata-Version: 2.3
Name: hmdriver2
Version: 1.4.4
Summary: UI Automation Framework for Harmony Next
License: MIT
Author: codematrixer
Author-email: chenli_gogo@163.com
Requires-Python: >=3.8,<4.0
Classifier: License :: OSI Approved :: MIT License
Classifier: Programming Language :: Python :: 3
Classifier: Programming Language :: Python :: 3.8
Classifier: Programming Language :: Python :: 3.9
Classifier: Programming Language :: Python :: 3.10
Classifier: Programming Language :: Python :: 3.11
Classifier: Programming Language :: Python :: 3.12
Classifier: Programming Language :: Python :: 3.13
Provides-Extra: opencv-python
Requires-Dist: lxml (>=5.3.0,<6.0.0)
